[
  {
    "id": 1,
    "timestamp": "2025-12-20T11:39:32.181203",
    "category": "развлечения",
    "amount": 450.66
  },
  {
    "id": 2,
    "timestamp": "2025-12-20T11:39:32.181203",
    "category": "транспорт",
    "amount": 2942.02
  },
  {
    "id": 3,
    "timestamp": "2025-12-20T11:39:32.181203",
    "category": "транспорт",
    "amount": 2673.15
  },
  {
    "id": 4,
    "timestamp": "2025-12-20T11:39:32.181203",
    "category": "транспорт",
    "amount": 4300.98
  },
  {
    "id": 5,
    "timestamp": "2025-12-20T11:39:32.181203",
    "category": "транспорт",
    "amount": 4025.05
  },
  {
    "id": 6,
    "timestamp": "2025-12-20T11:39:32.181203",
    "category": "еда",
    "amount": 1102.46
  },
  {
    "id": 7,
    "timestamp": "2025-12-20T11:39:32.181203",
    "category": "покупки",
    "amount": 1725.6
  },
  {
    "id": 8,
    "timestamp": "2025-12-20T11:39:32.181203",
    "category": "здоровье",
    "amount": 1317.83
  },
  {
    "id": 9,
    "timestamp": "2025-12-20T11:39:32.181203",
    "category": "транспорт",
    "amount": 2023.48
  },
  {
    "id": 10,
    "timestamp": "2025-12-20T11:39:32.181203",
    "category": "развлечения",
    "amount": 4577.27
  },
  {
    "id": 11,
    "timestamp": "2025-12-20T11:39:32.196857",
    "category": "развлечения",
    "amount": 4079.53
  },
  {
    "id": 12,
    "timestamp": "2025-12-20T11:39:32.196857",
    "category": "развлечения",
    "amount": 775.38
  },
  {
    "id": 13,
    "timestamp": "2025-12-20T11:39:32.196857",
    "category": "покупки",
    "amount": 141.97
  }
]